pythonsum/__init__.py
pythonsum/pysum.py
pythonsum-0.0.1.dist-info/LICENSE
pythonsum-0.0.1.dist-info/METADATA
pythonsum-0.0.1.dist-info/WHEEL
pythonsum-0.0.1.dist-info/top_level.txt
pythonsum-0.0.1.dist-info/RECORD
